[{"Bankcashbuy":"27.605","Bankcashsold":"28.275","Bankbuy":"\n                        27.93\n                    ","Banksold":"\n                        28.08\n                    ","ForwardBuyorSell":"查詢","Historicalrate":"查詢"},{"Bankcashbuy":"3.449","Bankcashsold":"3.653","Bankbuy":"\n                        3.57\n                    ","Banksold":"\n                        3.64\n                    ","ForwardBuyorSell":"查詢","Historicalrate":"查詢"},{"Bankcashbuy":"37.41","Bankcashsold":"39.53","Bankbuy":"\n                        38.305\n                    ","Banksold":"\n                        38.935\n                    ","ForwardBuyorSell":"查詢","Historicalrate":"查詢"},{"Bankcashbuy":"20.36","Bankcashsold":"21.14","Bankbuy":"\n                        20.575\n                    ","Banksold":"\n                        20.92\n                    ","ForwardBuyorSell":"查詢","Historicalrate":"查詢"},{"Bankcashbuy":"21.76","Bankcashsold":"22.67","Bankbuy":"\n                        22.09\n                    ","Banksold":"\n                        22.42\n                    ","ForwardBuyorSell":"查詢","Historicalrate":"查詢"},{"Bankcashbuy":"20.07","Bankcashsold":"20.98","Bankbuy":"\n                        20.54\n                    ","Banksold":"\n                        20.76\n                    ","ForwardBuyorSell":"查詢","Historicalrate":"查詢"},{"Bankcashbuy":"29.66","Bankcashsold":"30.86","Bankbuy":"\n                        30.27\n                    ","Banksold":"\n                        30.66\n                    ","ForwardBuyorSell":"查詢","Historicalrate":"查詢"},{"Bankcashbuy":"0.245","Bankcashsold":"0.2578","Bankbuy":"\n                        0.252\n                    ","Banksold":"\n                        0.2566\n                    ","ForwardBuyorSell":"查詢","Historicalrate":"查詢"},{"Bankcashbuy":"-","Bankcashsold":"-","Bankbuy":"\n                        1.899\n                    ","Banksold":"\n                        1.989\n                    ","ForwardBuyorSell":"查詢","Historicalrate":"查詢"},{"Bankcashbuy":"2.84","Bankcashsold":"3.36","Bankbuy":"\n                        3.17\n                    ","Banksold":"\n                        3.29\n                    ","ForwardBuyorSell":"查詢","Historicalrate":"查詢"},{"Bankcashbuy":"19.14","Bankcashsold":"19.99","Bankbuy":"\n                        19.47\n                    ","Banksold":"\n                        19.77\n                    ","ForwardBuyorSell":"查詢","Historicalrate":"查詢"},{"Bankcashbuy":"0.7268","Bankcashsold":"0.9168","Bankbuy":"\n                        0.8362\n                    ","Banksold":"\n                        0.8822\n                    ","ForwardBuyorSell":"查詢","Historicalrate":"查詢"},{"Bankcashbuy":"0.4807","Bankcashsold":"0.6137","Bankbuy":"\n                        -\n                    ","Banksold":"\n                        -\n                    ","ForwardBuyorSell":"查詢","Historicalrate":"查詢"},{"Bankcashbuy":"0.00158","Bankcashsold":"0.00228","Bankbuy":"\n                        -\n                    ","Banksold":"\n                        -\n                    ","ForwardBuyorSell":"查詢","Historicalrate":"查詢"},{"Bankcashbuy":"32.27","Bankcashsold":"33.61","Bankbuy":"\n                        32.785\n                    ","Banksold":"\n                        33.385\n                    ","ForwardBuyorSell":"查詢","Historicalrate":"查詢"},{"Bankcashbuy":"0.02278","Bankcashsold":"0.02668","Bankbuy":"\n                        -\n                    ","Banksold":"\n                        -\n                    ","ForwardBuyorSell":"查詢","Historicalrate":"查詢"},{"Bankcashbuy":"0.00097","Bankcashsold":"0.00138","Bankbuy":"\n                        -\n                    ","Banksold":"\n                        -\n                    ","ForwardBuyorSell":"查詢","Historicalrate":"查詢"},{"Bankcashbuy":"5.641","Bankcashsold":"7.121","Bankbuy":"\n                        -\n                    ","Banksold":"\n                        -\n                    ","ForwardBuyorSell":"查詢","Historicalrate":"查詢"},{"Bankcashbuy":"4.226","Bankcashsold":"4.388","Bankbuy":"\n                        4.293\n                    ","Banksold":"\n                        4.353\n                    ","ForwardBuyorSell":"查詢","Historicalrate":"查詢"}]