[{"Bankcashbuy":"31.27","Bankcashsold":"31.94","Bankbuy":"\n                        31.595\n                    ","Banksold":"\n                        31.745\n                    ","ForwardBuyorSell":"查詢","Historicalrate":"查詢"},{"Bankcashbuy":"3.879","Bankcashsold":"4.083","Bankbuy":"\n                        4\n                    ","Banksold":"\n                        4.07\n                    ","ForwardBuyorSell":"查詢","Historicalrate":"查詢"},{"Bankcashbuy":"33.78","Bankcashsold":"35.9","Bankbuy":"\n                        34.675\n                    ","Banksold":"\n                        35.305\n                    ","ForwardBuyorSell":"查詢","Historicalrate":"查詢"},{"Bankcashbuy":"19.54","Bankcashsold":"20.32","Bankbuy":"\n                        19.755\n                    ","Banksold":"\n                        20.1\n                    ","ForwardBuyorSell":"查詢","Historicalrate":"查詢"},{"Bankcashbuy":"22.54","Bankcashsold":"23.45","Bankbuy":"\n                        22.87\n                    ","Banksold":"\n                        23.2\n                    ","ForwardBuyorSell":"查詢","Historicalrate":"查詢"},{"Bankcashbuy":"21.47","Bankcashsold":"22.38","Bankbuy":"\n                        21.94\n                    ","Banksold":"\n                        22.16\n                    ","ForwardBuyorSell":"查詢","Historicalrate":"查詢"},{"Bankcashbuy":"30.93","Bankcashsold":"32.13","Bankbuy":"\n                        31.54\n                    ","Banksold":"\n                        31.93\n                    ","ForwardBuyorSell":"查詢","Historicalrate":"查詢"},{"Bankcashbuy":"0.2086","Bankcashsold":"0.2214","Bankbuy":"\n                        0.2154\n                    ","Banksold":"\n                        0.2204\n                    ","ForwardBuyorSell":"查詢","Historicalrate":"查詢"},{"Bankcashbuy":"-","Bankcashsold":"-","Bankbuy":"\n                        1.695\n                    ","Banksold":"\n                        1.785\n                    ","ForwardBuyorSell":"查詢","Historicalrate":"查詢"},{"Bankcashbuy":"2.41","Bankcashsold":"2.93","Bankbuy":"\n                        2.74\n                    ","Banksold":"\n                        2.86\n                    ","ForwardBuyorSell":"查詢","Historicalrate":"查詢"},{"Bankcashbuy":"17.2","Bankcashsold":"18.05","Bankbuy":"\n                        17.53\n                    ","Banksold":"\n                        17.83\n                    ","ForwardBuyorSell":"查詢","Historicalrate":"查詢"},{"Bankcashbuy":"0.7083","Bankcashsold":"0.8983","Bankbuy":"\n                        0.8177\n                    ","Banksold":"\n                        0.8637\n                    ","ForwardBuyorSell":"查詢","Historicalrate":"查詢"},{"Bankcashbuy":"0.463","Bankcashsold":"0.596","Bankbuy":"\n                        -\n                    ","Banksold":"\n                        -\n                    ","ForwardBuyorSell":"查詢","Historicalrate":"查詢"},{"Bankcashbuy":"0.00168","Bankcashsold":"0.00238","Bankbuy":"\n                        -\n                    ","Banksold":"\n                        -\n                    ","ForwardBuyorSell":"查詢","Historicalrate":"查詢"},{"Bankcashbuy":"29.88","Bankcashsold":"31.22","Bankbuy":"\n                        30.395\n                    ","Banksold":"\n                        30.995\n                    ","ForwardBuyorSell":"查詢","Historicalrate":"查詢"},{"Bankcashbuy":"0.02041","Bankcashsold":"0.02431","Bankbuy":"\n                        -\n                    ","Banksold":"\n                        -\n                    ","ForwardBuyorSell":"查詢","Historicalrate":"查詢"},{"Bankcashbuy":"0.00108","Bankcashsold":"0.00149","Bankbuy":"\n                        -\n                    ","Banksold":"\n                        -\n                    ","ForwardBuyorSell":"查詢","Historicalrate":"查詢"},{"Bankcashbuy":"5.799","Bankcashsold":"7.279","Bankbuy":"\n                        -\n                    ","Banksold":"\n                        -\n                    ","ForwardBuyorSell":"查詢","Historicalrate":"查詢"},{"Bankcashbuy":"4.334","Bankcashsold":"4.496","Bankbuy":"\n                        4.401\n                    ","Banksold":"\n                        4.461\n                    ","ForwardBuyorSell":"查詢","Historicalrate":"查詢"}]